{
  "gearhaven_plaza": {
    "name": "Cogwheel Plaza",
    "faction": "luminara",
    "description": "Steam hisses from pipes and gears grind beneath your feet. Merchants shout over the clatter while travelers mingle in the plaza.",
    "exits": [
      "n",
      "e",
      "s"
    ],
    "links": {
      "n": "gearhaven_workshop",
      "e": "neutral_crossroads",
      "s": "shadowfen_camp"
    },
    "npcs": [
      "thaldo_tinkerer",
      "gilda_crafter",
      "rogar_trainer",
      "belena_trainer",
      "bard_npc",
      "druid_npc",
      "joran_barkeep"
    ],
    "spawns": [
      "rogue_clockwork"
    ]
  },
  "gearhaven_workshop": {
    "name": "Gearhaven Workshop",
    "faction": "luminara",
    "description": "Inventors toil with strange contraptions here, the air thick with the scent of oil and magic.",
    "exits": [
      "s"
    ],
    "links": {
      "s": "gearhaven_plaza"
    },
    "npcs": [
      "thaldo_tinkerer",
      "gilda_crafter"
    ],
    "spawns": []
  },
  "shadowfen_camp": {
    "name": "Shadowfen Camp",
    "faction": "umbra",
    "description": "A dark encampment surrounded by murky waters where warriors of Umbra sharpen their blades.",
    "exits": [
      "n",
      "e"
    ],
    "links": {
      "n": "gearhaven_plaza",
      "e": "shadowfen_bog"
    },
    "npcs": [
      "bog_hunter",
      "shadra_shaman",
      "gruk_trainer",
      "morga_shadow",
      "drezz_smith"
    ],
    "spawns": [
      "goblin_raider"
    ]
  },
  "shadowfen_bog": {
    "name": "Shadowfen Bog",
    "faction": "umbra",
    "description": "Thick mist blankets the soggy ground and the croak of unseen creatures echoes all around.",
    "exits": [
      "w"
    ],
    "links": {
      "w": "shadowfen_camp"
    },
    "npcs": [],
    "spawns": [
      "bog_creeper"
    ]
  },
  "neutral_crossroads": {
    "name": "Crossroads",
    "faction": "neutral",
    "description": "A dusty intersection where caravans pause and news from all factions is traded.",
    "exits": [
      "w"
    ],
    "links": {
      "w": "gearhaven_plaza"
    },
    "npcs": [
      "ranger_npc",
      "traveling_merchant"
    ],
    "spawns": []
  }
}
