{
  "barbarian": [
    {"level": 1, "skills": ["slash", "block"]},
    {"level": 20, "skills": ["slash_2", "block_2"]},
    {"level": 30, "skills": ["war_cry"]},
    {"level": 40, "skills": ["slash_3", "block_3"]},
    {"level": 60, "skills": ["war_cry_2"]}
  ],
  "sorceress": [
    {"level": 1, "skills": ["fireball", "frostbolt"]},
    {"level": 20, "skills": ["fireball_2", "frostbolt_2"]},
    {"level": 30, "skills": ["arcane_blast"]},
    {"level": 40, "skills": ["fireball_3", "frostbolt_3"]},
    {"level": 60, "skills": ["arcane_blast_2"]}
  ],
  "amazon": [
    {"level": 1, "skills": ["shoot", "track"]},
    {"level": 20, "skills": ["shoot_2", "track_2"]},
    {"level": 30, "skills": ["rapid_fire"]},
    {"level": 40, "skills": ["shoot_3", "track_3"]},
    {"level": 60, "skills": ["rapid_fire_2"]}
  ],
  "necromancer": [
    {"level": 1, "skills": ["drain", "raise_dead"]},
    {"level": 20, "skills": ["drain_2", "raise_dead_2"]},
    {"level": 30, "skills": ["bone_spear"]},
    {"level": 40, "skills": ["drain_3", "raise_dead_3"]},
    {"level": 60, "skills": ["bone_spear_2"]}
  ],
  "druid": [
    {"level": 1, "skills": ["entangle", "regrowth"]},
    {"level": 20, "skills": ["entangle_2", "regrowth_2"]},
    {"level": 30, "skills": ["bear_form"]},
    {"level": 40, "skills": ["entangle_3", "regrowth_3"]},
    {"level": 60, "skills": ["bear_form_2"]}
  ]
}
